[
  {
    "type": "road",
    "tag": "road",
    "icon": "&#x1F6AB;",
    "title": "Balule Camp - Closed",
    "desc": "Community reports - 1 report. Source: krugerstatus.co.za",
    "time": "2026-07-21T18:08:15.346Z",
    "source": "Kruger Status"
  },
  {
    "type": "road",
    "tag": "road",
    "icon": "&#x1F6AB;",
    "title": "Lower Sabie Camp - Closed",
    "desc": "Community reports - 4 reports. Source: krugerstatus.co.za",
    "time": "2026-07-22T08:12:58.561Z",
    "source": "Kruger Status"
  },
  {
    "type": "road",
    "tag": "road",
    "icon": "&#x1F7E1;",
    "title": "Letaba Camp - Limited access",
    "desc": "Community reports - 4 reports. Source: krugerstatus.co.za",
    "time": "2026-07-21T17:30:02.463Z",
    "source": "Kruger Status"
  },
  {
    "type": "road",
    "tag": "road",
    "icon": "&#x1F7E1;",
    "title": "Orpen Camp - Limited access",
    "desc": "Community reports - 1 report. Source: krugerstatus.co.za",
    "time": "2026-07-21T18:42:29.693Z",
    "source": "Kruger Status"
  },
  {
    "type": "road",
    "tag": "road",
    "icon": "&#x1F7E1;",
    "title": "Crocodile Bridge Camp - Limited access",
    "desc": "Community reports - 3 reports. Source: krugerstatus.co.za",
    "time": "2026-07-22T08:11:18.887Z",
    "source": "Kruger Status"
  },
  {
    "type": "road",
    "tag": "road",
    "icon": "&#x1F7E2;",
    "title": "S106 Road - Open",
    "desc": "Community reports - 1 report. Source: krugerstatus.co.za",
    "time": "2026-07-21T11:12:42.411Z",
    "source": "Kruger Status"
  },
  {
    "type": "road",
    "tag": "road",
    "icon": "&#x1F3D5;",
    "title": "Olifants Camp - Open",
    "desc": "Community reports - 1 report. Source: krugerstatus.co.za",
    "time": "2026-07-21T17:03:00.654Z",
    "source": "Kruger Status"
  },
  {
    "type": "road",
    "tag": "road",
    "icon": "&#x26AA;",
    "title": "Satara Camp - Last known: open",
    "desc": "Community reports - 2 reports. Source: krugerstatus.co.za",
    "time": "2026-07-21T18:36:50.062Z",
    "source": "Kruger Status"
  },
  {
    "type": "road",
    "tag": "road",
    "icon": "&#x26AA;",
    "title": "Malelane Gate - Last known: closed",
    "desc": "Community reports - 8 reports. Source: krugerstatus.co.za",
    "time": "2026-07-22T06:49:33.040Z",
    "source": "Kruger Status"
  },
  {
    "type": "road",
    "tag": "road",
    "icon": "&#x26AA;",
    "title": "H1 2 Road - Last known: limited",
    "desc": "Community reports - 5 reports. Source: krugerstatus.co.za",
    "time": "2026-07-22T10:01:02.233Z",
    "source": "Kruger Status"
  }
]